geoai_vlm/__init__.py
geoai_vlm/describer.py
geoai_vlm/downloader.py
geoai_vlm/geometry.py
geoai_vlm/io.py
geoai_vlm/pipeline.py
geoai_vlm/prompts.py
geoai_vlm-0.1.4.dist-info/METADATA
geoai_vlm-0.1.4.dist-info/WHEEL
geoai_vlm-0.1.4.dist-info/licenses/LICENSE
geoai_vlm-0.1.4.dist-info/RECORD
