Metadata-Version: 2.4
Name: geoai-vlm
Version: 0.1.4
Summary: Geospatial Vision-Language Model analysis for street-level imagery. Download Mapillary images by location and generate structured descriptions using VLMs.
Project-URL: Homepage, https://github.com/yunusserhat/geoai-vlm
Project-URL: Documentation, https://github.com/yunusserhat/geoai-vlm#readme
Project-URL: Repository, https://github.com/yunusserhat/geoai-vlm
Project-URL: Issues, https://github.com/yunusserhat/geoai-vlm/issues
Author-email: Yunus Serhat Bıçakçı <yunus.serhat@marmara.edu.tr>, Yunus Serhat Bıçakçı <yunusserhat.bicakci@glasgow.ac.uk>
License: MIT
License-File: LICENSE
Keywords: geoai,geoparquet,geospatial,mapillary,street-view,urban-analytics,vision-language-model,vlm
Classifier: Development Status :: 3 - Alpha
Classifier: Intended Audience :: Science/Research
Classifier: License :: OSI Approved :: MIT License
Classifier: Programming Language :: Python :: 3
Classifier: Programming Language :: Python :: 3.9
Classifier: Programming Language :: Python :: 3.10
Classifier: Programming Language :: Python :: 3.11
Classifier: Programming Language :: Python :: 3.12
Classifier: Topic :: Scientific/Engineering :: Artificial Intelligence
Classifier: Topic :: Scientific/Engineering :: GIS
Requires-Python: >=3.9
Requires-Dist: accelerate>=1.12.0
Requires-Dist: geopandas>=1.1.2
Requires-Dist: haversine>=2.9.0
Requires-Dist: numpy<2.dev0
Requires-Dist: pandas>=2.3.3
Requires-Dist: pillow>=10.0.0
Requires-Dist: pyarrow>=16.0.0
Requires-Dist: qwen-vl-utils>=0.0.14
Requires-Dist: requests>=2.32.5
Requires-Dist: shapely>=2.1.2
Requires-Dist: torch>=2.9.0
Requires-Dist: tqdm>=4.67.0
Requires-Dist: transformers>=4.57.3
Requires-Dist: vllm>=0.13.0
Requires-Dist: zensvi>=1.4.3
Provides-Extra: dev
Requires-Dist: black>=25.12.0; extra == 'dev'
Requires-Dist: mypy>=1.19.0; extra == 'dev'
Requires-Dist: pytest-cov>=7.0.0; extra == 'dev'
Requires-Dist: pytest>=9.0.0; extra == 'dev'
Requires-Dist: ruff>=0.14.10; extra == 'dev'
